mdh/__init__.py
mdh/kinematic_chain.py
mdh/link.py
mdh/robots.py
mdh-0.1.3.dist-info/LICENSE
mdh-0.1.3.dist-info/WHEEL
mdh-0.1.3.dist-info/METADATA
mdh-0.1.3.dist-info/RECORD
