Metadata-Version: 2.1
Name: mdh
Version: 0.1.3
Summary: modified dh
Home-page: https://pypi.org/project/mdh/
License: MIT
Keywords: serial manipulators,robotics,kinematics,dh,denavit,hartenberg,denavit–hartenberg
Author: walchko
Author-email: walchko@users.noreply.github.com
Requires-Python: >=3.6
Classifier: Development Status :: 4 - Beta
Classifier: Intended Audience :: Developers
Classifier: License :: OSI Approved :: MIT License
Classifier: Operating System :: OS Independent
Classifier: Programming Language :: Python :: 3
Classifier: Programming Language :: Python :: 3.6
Classifier: Programming Language :: Python :: 3.7
Classifier: Programming Language :: Python :: 3.8
Classifier: Topic :: Software Development :: Libraries
Classifier: Topic :: Software Development :: Libraries :: Application Frameworks
Classifier: Topic :: Software Development :: Libraries :: Python Modules
Requires-Dist: attrs
Requires-Dist: colorama
Requires-Dist: importlib-metadata; python_version < "3.8"
Requires-Dist: numpy (>=1.9)
Requires-Dist: scipy (>=1.0)
Project-URL: Repository, https://github.com/MultipedRobotics/dh
